tflask/__init__.py
tflask/tclient.py
tflask/tfblueprints.py
tflask/tfflask.py
tflask/tfroutes.py
tflask/tfworker.py
tflask/tservice.py
tfthrift-0.0.1b0.dist-info/DESCRIPTION.rst
tfthrift-0.0.1b0.dist-info/METADATA
tfthrift-0.0.1b0.dist-info/RECORD
tfthrift-0.0.1b0.dist-info/WHEEL
tfthrift-0.0.1b0.dist-info/metadata.json
tfthrift-0.0.1b0.dist-info/top_level.txt
thrift_protocol/Rpc.py
thrift_protocol/__init__.py
thrift_protocol/constants.py
thrift_protocol/ttypes.py
