Metadata-Version: 2.0
Name: tfthrift
Version: 0.0.1b0
Summary: tfthrift
Home-page: UNKNOWN
Author: tf
Author-email: tf@thefair.net.cn
License: MIT
Platform: UNKNOWN
Classifier: Development Status :: 4 - Beta
Classifier: Intended Audience :: Developers
Classifier: Topic :: Software Development :: Build Tools
Classifier: License :: OSI Approved :: MIT License
Classifier: Programming Language :: Python :: 3.6
